neuron_image_denoise/__init__.py
neuron_image_denoise/_filter.cp310-win_amd64.pyd
neuron_image_denoise/_filter.pyx
neuron_image_denoise/filter.py
neuron_image_denoise-0.0.4.dist-info/LICENSE
neuron_image_denoise-0.0.4.dist-info/METADATA
neuron_image_denoise-0.0.4.dist-info/WHEEL
neuron_image_denoise-0.0.4.dist-info/top_level.txt
neuron_image_denoise-0.0.4.dist-info/RECORD
