Metadata-Version: 2.1
Name: neuron-image-denoise
Version: 0.0.4
Summary: Fluorescent neuron image denoising tools
Author-email: Zuohan Zhao <zzhmark@126.com>
License: MIT License
Project-URL: GitHub Project, https://github.com/SEU-ALLEN-codebase/neuron-image-denoise-py
Project-URL: Documentation, https://SEU-ALLEN-codebase.github.io/neuron-image-denoise-py
Keywords: vaa3d,neuron-morphology,image-processing
Classifier: Programming Language :: Python :: 3
Classifier: License :: OSI Approved :: MIT License
Classifier: Operating System :: OS Independent
Requires-Python: >=3.10
License-File: LICENSE
Requires-Dist: numpy
Requires-Dist: scikit-image
Provides-Extra: docs
Requires-Dist: pdoc ; extra == 'docs'
